{
  "-OncUMDDSh5sIsZw8FB4": {
    "ativa": true,
    "criado_em": 1773427063371,
    "itens": [
      {
        "loops": 1,
        "nome": "1 andar sem filas",
        "tipo": "audio/wav",
        "url": "https://firebasestorage.googleapis.com/v0/b/anucio-web.firebasestorage.app/o/users%2FLh3RfmXbLhYdlq3UYuMANHzB14i1%2Faudios%2F1773427020175_1_andar_sem_filas.wav?alt=media&token=7dee0b38-e704-41e3-81ee-25d49b5b6ec2"
      }
    ],
    "nome": "Teste"
  },
  "-OnmVltzITnq1yamQg3p": {
    "ativa": true,
    "criado_em": 1773595205406,
    "nome": "ADM"
  }
}